{"state":"trained","evaluationEntity":{"id":"625e372a-6f15-4a15-899f-1bf28bcbfd93","analysedDataType":"none","dataResult":{}},"preferredFilename":"BetterRestML 1","activityEntities":["trainingFinished",[{"title":"Training Completed","id":"B55D91F4-2336-4150-9D9F-3207BE721E49","subtitle":"BetterRestML 1","createdDate":"2025-03-10T19:07:51Z","event":"trainingFinished"}],"experimentCreated",[{"subtitle":"BetterRestML 1","id":"647BE6B5-2060-4C71-9D69-4275BC1C364F","event":"experimentCreated","createdDate":"2025-03-10T19:04:55Z","title":"Model Source Created"}],"trainingStarted",[{"event":"trainingStarted","createdDate":"2025-03-10T19:07:50Z","id":"1D9AD783-4B94-428B-A7C7-F965D4E07FDB","title":"Training Started","subtitle":"BetterRestML 1"}],"trainingDataAdded",[{"id":"D605C20F-2435-4901-B388-B275A981936F","title":"Training Data Added","createdDate":"2025-03-10T19:06:10Z","subtitle":"BetterRest.csv","event":"trainingDataAdded"}]],"version":"1.0","trainingEntity":{"startTime":"2025-03-10T19:07:50Z","checkpointMetrics":{},"trainingAccuracy":177.06208892898437,"featureExtractionCheckpointMayBeAvailable":false,"validationAccuracy":176.87807805760778,"finishTime":"2025-03-10T19:07:51Z","analysedDataType":"datasource","snapshottableCheckpoints":{},"dataSourceID":"8D39E9EF-783F-429F-B2CF-281DB15D6D5B","progress":[],"validationResults":{"generalRegressor":{"rootMeanSquaredError":176.87807805760778,"maximumError":694.8439790224293}},"trainingResults":{"generalRegressor":{"rootMeanSquaredError":177.06208892898437,"maximumError":700.7884351199755}},"dataResult":{"dataAnalysis":{"objectDetectorAnalysis":{"details":{}},"issues":[{"description":"Data has 10000 rows","severity":"info"}],"classifierAnalysis":{},"regressorAnalysis":{"targetRange":[19216,45224]},"summary":{"canUseValidation":1,"sampleCount":10000}},"columnValues":["31,500.00, 32,400.00, 26,100.00, 40,500.00, 19,800.00, 27,000.00, 20,700.00, 21,600.00, 41,400.00, 34,200.00, 21,600.00, 78,300.00, 32,400.00, 28,800.00, 18,900.00, 18,000.00, 28,800.00, 18,000.00, 7,200.00, 35,100.00, 24,300.00, 35,100.00, 34,200.00, 27,900.00, 30,600.00, 69,300.00, 35,100.00, 34,200.00, 34,200.00, 23,400.00","9.00, 5.00, 6.50, 8.75, 6.00, 7.50, 9.25, 6.00, 9.25, 6.75, 5.25, 9.25, 10.00, 8.75, 8.25, 6.25, 10.00, 6.25, 10.00, 9.50, 5.00, 7.50, 6.25, 8.00, 8.00, 6.50, 8.00, 10.00, 8.25, 8.00","6.00, 2.00, 10.00, 4.00, 3.00, 1.00, 1.00, 3.00, 5.00, 8.00, 3.00, 8.00, 2.00, 3.00, 1.00, 2.00, 3.00, 2.00, 1.00, 4.00, 2.00, 1.00, 1.00, 4.00, 3.00, 7.00, 4.00, 4.00, 1.00, 3.00","38,230.00, 20,180.00, 31,989.00, 35,258.00, 24,487.00, 28,300.00, 34,548.00, 24,557.00, 37,836.00, 31,340.00, 21,874.00, 40,405.00, 38,076.00, 34,265.00, 30,936.00, 24,665.00, 39,007.00, 24,578.00, 37,267.00, 37,878.00, 20,220.00, 28,400.00, 23,882.00, 32,427.00, 31,699.00, 29,670.00, 32,789.00, 39,792.00, 30,935.00, 31,701.00"],"dataSourceID":"8D39E9EF-783F-429F-B2CF-281DB15D6D5B","itemsCount":10000,"dataURL":"file:\/\/\/Users\/development\/Documents\/grind\/BetterRest\/BetterRest.csv","columnTypes":["Double","Double","Double","Double"],"createdDate":"2025-03-10T19:06:10Z","columns":["wake","estimatedSleep","coffee","actualSleep"],"targetRange":[19216,45224]}},"createdDate":"2025-03-10T19:04:55Z","settingEntity":{"handActionClassifierAugmentations":[],"algorithmType":"maxEnt","suggestedColumns":["wake","estimatedSleep","coffee","actualSleep"],"transferLearningEmbeddingType":"dynamic","seedType":"default","suggestedColumnTypes":["Double","Double","Double","Double"],"handPoseClassifierAugmentations":[],"harVideoAugmentations":0,"featureNames":["wake","estimatedSleep","coffee"],"generalRegressorType":{"auto":{}},"suggestedColumnValues":["31,500.00, 32,400.00, 26,100.00, 40,500.00, 19,800.00, 27,000.00, 20,700.00, 21,600.00, 41,400.00, 34,200.00, 21,600.00, 78,300.00, 32,400.00, 28,800.00, 18,900.00, 18,000.00, 28,800.00, 18,000.00, 7,200.00, 35,100.00, 24,300.00, 35,100.00, 34,200.00, 27,900.00, 30,600.00, 69,300.00, 35,100.00, 34,200.00, 34,200.00, 23,400.00","9.00, 5.00, 6.50, 8.75, 6.00, 7.50, 9.25, 6.00, 9.25, 6.75, 5.25, 9.25, 10.00, 8.75, 8.25, 6.25, 10.00, 6.25, 10.00, 9.50, 5.00, 7.50, 6.25, 8.00, 8.00, 6.50, 8.00, 10.00, 8.25, 8.00","6.00, 2.00, 10.00, 4.00, 3.00, 1.00, 1.00, 3.00, 5.00, 8.00, 3.00, 8.00, 2.00, 3.00, 1.00, 2.00, 3.00, 2.00, 1.00, 4.00, 2.00, 1.00, 1.00, 4.00, 3.00, 7.00, 4.00, 4.00, 1.00, 3.00","38,230.00, 20,180.00, 31,989.00, 35,258.00, 24,487.00, 28,300.00, 34,548.00, 24,557.00, 37,836.00, 31,340.00, 21,874.00, 40,405.00, 38,076.00, 34,265.00, 30,936.00, 24,665.00, 39,007.00, 24,578.00, 37,267.00, 37,878.00, 20,220.00, 28,400.00, 23,882.00, 32,427.00, 31,699.00, 29,670.00, 32,789.00, 39,792.00, 30,935.00, 31,701.00"],"taskType":"generalRegresor","styleTransferAlgorithmType":"image","targetColumn":"actualSleep","augmentations":[]},"modelEntity":{"id":"983D02A9-663A-42D1-A99E-E09D7C44F6DE","modifiedDate":"2025-03-10T19:04:55Z","preferredFilename":"","version":"1.0","modelURL":"Models\/BetterRestML%201.mlmodel","createdDate":"2025-03-10T19:04:55Z","experimentID":"381D339B-2721-49CD-8624-4EFB1E3A0C30","title":""},"id":"381D339B-2721-49CD-8624-4EFB1E3A0C30","evaluationContainerEntity":{"createdDate":"2025-03-10T19:07:59Z","previewType":"tabularRegressor","testingEvaluationEntity":{"id":"39b1066b-3a4e-4334-a7c2-39d3555d9c41","analysedDataType":"none","createdDate":"2025-03-10T19:04:55Z","dataResult":{"createdDate":"2025-03-10T19:06:10Z"}},"modifiedDate":"2025-03-10T19:07:59Z","validationEvaluationEntity":{"createdDate":"2025-03-10T19:04:55Z","id":"c4aaec61-8d87-4192-84f4-210a8c52a455","dataResult":{"createdDate":"2025-03-10T19:06:10Z"},"analysedDataType":"auto","evaluationResult":{"generalRegressor":{"maximumError":694.8439790224293,"rootMeanSquaredError":176.87807805760778}}},"trainingEvaluationEntity":{"dataSourceID":"8D39E9EF-783F-429F-B2CF-281DB15D6D5B","dataResult":{"itemsCount":10000,"dataURL":"file:\/\/\/Users\/development\/Documents\/grind\/BetterRest\/BetterRest.csv","createdDate":"2025-03-10T19:06:10Z","dataAnalysis":{"summary":{"sampleCount":10000,"canUseValidation":1},"objectDetectorAnalysis":{"details":{}},"regressorAnalysis":{"targetRange":[19216,45224]},"issues":[{"severity":"info","description":"Data has 10000 rows"}],"classifierAnalysis":{}},"targetRange":[19216,45224],"dataSourceID":"8D39E9EF-783F-429F-B2CF-281DB15D6D5B"},"evaluationResult":{"generalRegressor":{"rootMeanSquaredError":177.06208892898437,"maximumError":700.7884351199755}},"id":"64fc8017-48f2-41ce-bb59-0fdf2ca30b3e","createdDate":"2025-03-10T19:04:55Z","analysedDataType":"none"},"id":"fbcb85f2-d4f7-42ef-b9e2-1d479fbb3c31","evaluationEntities":[{"dataResult":{},"createdDate":"2025-03-10T19:07:59Z","analysedDataType":"none","id":"278699c7-9987-47db-9d9a-30ad5911efab"}]},"title":"BetterRestML 1","evaluationState":"uninitialized","snapshotRole":{"withoutSnapshots":0},"contentDataResult":{"createdDate":"2025-03-10T19:06:10Z"},"validationEntity":{"dataResult":{"createdDate":"2025-03-10T19:06:10Z"},"analysedDataType":"auto"},"modifiedDate":"2025-03-10T19:07:59Z"}